{
    "items_id": "fc85a796c16dc65c8ccad963f6fb3904",
    "scientific_name": "Orthetrum cancellatum",
    "local_names": [
        "Black-tailed skimmer"
    ],
    "description": "",
    "distribution": "",
    "flight_period": "",
    "behaviour": "",
    "habitat": "",
    "size": {
        "length": "45-50 mm",
        "wingspan": "70-80 mm"
    },
    "similar_species": [],
    "red_list": {
        "habitats_directive": "No",
        "red_list_EU27": "Least Concern",
        "red_list_europe": "Least Concern",
        "red_list_mediterranean": "Least Concern",
        "EU27_endemic": "No",
        "red_list_europe_endemic": "No",
        "trend_europe": "Stable"
    },
    "author_citation": "(Linnaeus, 1758)",
    "images": {
        "cloud_name": "dragonflies",
        "all": []
    }
}